choreo_GUI/Pyodide_worker.js
choreo_GUI/__init__.py
choreo_GUI/anim.js
choreo_GUI/choreo_GUI.js
choreo_GUI/coi-serviceworker.min.js
choreo_GUI/http_server.py
choreo_GUI/index.html
choreo_GUI/manage_gallery.py
choreo_GUI/metadata.py
choreo_GUI/run.py
choreo_GUI/assets/main.min.js
choreo_GUI/assets/css/academicons.css
choreo_GUI/assets/css/academicons.min.css
choreo_GUI/assets/css/choreo_GUI.css
choreo_GUI/assets/css/choreo_anims.css
choreo_GUI/assets/css/collapse.css
choreo_GUI/assets/css/fake.css
choreo_GUI/assets/css/jquery-ui-1.10.2.custom.min.css
choreo_GUI/assets/css/main.css
choreo_GUI/assets/css/main.scss
choreo_GUI/assets/css/roundslider.min.css
choreo_GUI/assets/css/style.css
choreo_GUI/assets/css/treejs.css
choreo_GUI/assets/css/treejs.min.css
choreo_GUI/assets/css/w3.css
choreo_GUI/assets/fonts/academicons.eot
choreo_GUI/assets/fonts/academicons.svg
choreo_GUI/assets/fonts/academicons.ttf
choreo_GUI/assets/fonts/academicons.woff
choreo_GUI/assets/fonts/fa-brands-400.eot
choreo_GUI/assets/fonts/fa-brands-400.svg
choreo_GUI/assets/fonts/fa-brands-400.ttf
choreo_GUI/assets/fonts/fa-brands-400.woff
choreo_GUI/assets/fonts/fa-brands-400.woff2
choreo_GUI/assets/fonts/fa-regular-400.eot
choreo_GUI/assets/fonts/fa-regular-400.svg
choreo_GUI/assets/fonts/fa-regular-400.ttf
choreo_GUI/assets/fonts/fa-regular-400.woff
choreo_GUI/assets/fonts/fa-regular-400.woff2
choreo_GUI/assets/fonts/fa-solid-900.eot
choreo_GUI/assets/fonts/fa-solid-900.svg
choreo_GUI/assets/fonts/fa-solid-900.ttf
choreo_GUI/assets/fonts/fa-solid-900.woff
choreo_GUI/assets/fonts/fa-solid-900.woff2
choreo_GUI/assets/js/LoadLocalOrCDN.js
choreo_GUI/assets/js/_main.js
choreo_GUI/assets/js/collapse.js
choreo_GUI/assets/js/ffmpeg.min.js
choreo_GUI/assets/js/jquery-ui.min.js
choreo_GUI/assets/js/jquery.min.js
choreo_GUI/assets/js/jquery.ui.touch-punch.min.js
choreo_GUI/assets/js/npy.min.js
choreo_GUI/assets/js/roundslider.min.js
choreo_GUI/assets/js/tex-mml-chtml.js
choreo_GUI/assets/js/tree.min.js
choreo_gui-1.0.0rc0.dist-info/licenses/LICENSE
choreo_gui-1.0.0rc0.dist-info/licenses/LICENSES/LICENSE.txt
choreo_gui-1.0.0rc0.dist-info/licenses/LICENSES/OrdinaryDiffEq.jl_licence.txt
choreo_gui-1.0.0rc0.dist-info/licenses/LICENSES/Readme.md
choreo_gui-1.0.0rc0.dist-info/licenses/LICENSES/mpmath_license.txt
choreo_gui-1.0.0rc0.dist-info/licenses/LICENSES/network_vis_license.txt
choreo_gui-1.0.0rc0.dist-info/licenses/LICENSES/npyjs_licence.txt
choreo_gui-1.0.0rc0.dist-info/licenses/LICENSES/pyFFTW_license.txt
choreo_gui-1.0.0rc0.dist-info/licenses/LICENSES/scipy_license.txt
choreo_gui-1.0.0rc0.dist-info/licenses/LICENSES/treejs_licence.txt
choreo_gui-1.0.0rc0.dist-info/METADATA
choreo_gui-1.0.0rc0.dist-info/WHEEL
choreo_gui-1.0.0rc0.dist-info/entry_points.txt
choreo_gui-1.0.0rc0.dist-info/top_level.txt
choreo_gui-1.0.0rc0.dist-info/RECORD
