Metadata-Version: 2.4
Name: choreo_GUI
Version: 1.0.0rc0
Summary: A set of tools to compute periodic solutions to the Newtonian N-body problem
Author-email: Gabriel Fougeron <gabriel.fougeron@hotmail.fr>
License-Expression: BSD-2-Clause
Project-URL: Homepage, https://gabrielfougeron.github.io/choreo/
Project-URL: Documentation, https://gabrielfougeron.github.io/choreo-docs/
Project-URL: Repository, https://github.com/gabrielfougeron/choreo
Project-URL: Changelog, https://github.com/gabrielfougeron/choreo/releases/
Keywords: GUI,ODE,periodic,N-body,gravitation
Classifier: Development Status :: 2 - Pre-Alpha
Classifier: Programming Language :: Python :: 3
Classifier: Programming Language :: JavaScript
Classifier: Environment :: WebAssembly :: Emscripten
Classifier: Intended Audience :: Education
Classifier: Natural Language :: English
Classifier: Topic :: Scientific/Engineering :: Mathematics
Classifier: Topic :: Scientific/Engineering :: Physics
Requires-Python: >=3.10
License-File: LICENSE
License-File: LICENSES/LICENSE.txt
License-File: LICENSES/OrdinaryDiffEq.jl_licence.txt
License-File: LICENSES/Readme.md
License-File: LICENSES/mpmath_license.txt
License-File: LICENSES/network_vis_license.txt
License-File: LICENSES/npyjs_licence.txt
License-File: LICENSES/pyFFTW_license.txt
License-File: LICENSES/scipy_license.txt
License-File: LICENSES/treejs_licence.txt
Dynamic: license-file
